libsms/__init__.py
libsms/_client/__init__.py
libsms/_client/api/__init__.py
libsms/_client/api/analyses/__init__.py
libsms/_client/api/analyses/download_analysis_output_file.py
libsms/_client/api/analyses/download_tsv_zip.py
libsms/_client/api/analyses/fetch_experiment_analysis.py
libsms/_client/api/analyses/get_analysis_log.py
libsms/_client/api/analyses/get_analysis_plots.py
libsms/_client/api/analyses/get_analysis_plots_formatted.py
libsms/_client/api/analyses/get_analysis_status.py
libsms/_client/api/analyses/get_analysis_tsv.py
libsms/_client/api/analyses/get_analysis_tsv_formatted.py
libsms/_client/api/analyses/list_analyses.py
libsms/_client/api/analyses/run_experiment_analysis.py
libsms/_client/api/analyses/upload_analysis_module.py
libsms/_client/api/ecoli_sim/__init__.py
libsms/_client/api/ecoli_sim/get_latest_simulator.py
libsms/_client/api/ecoli_sim/get_parca_status.py
libsms/_client/api/ecoli_sim/get_parca_versions.py
libsms/_client/api/ecoli_sim/get_simulation_status.py
libsms/_client/api/ecoli_sim/get_simulation_versions.py
libsms/_client/api/ecoli_sim/get_simulation_worker_events.py
libsms/_client/api/ecoli_sim/get_simulator_status.py
libsms/_client/api/ecoli_sim/get_simulator_versions.py
libsms/_client/api/ecoli_sim/insert_simulator_version.py
libsms/_client/api/ecoli_sim/run_ecolisim.py
libsms/_client/api/ecoli_sim/run_parca.py
libsms/_client/api/simulations/__init__.py
libsms/_client/api/simulations/download_ecoli_simulation_data.py
libsms/_client/api/simulations/get_ecoli_simulation.py
libsms/_client/api/simulations/get_ecoli_simulation_data.py
libsms/_client/api/simulations/get_ecoli_simulation_log.py
libsms/_client/api/simulations/get_ecoli_simulation_log_detail.py
libsms/_client/api/simulations/get_ecoli_simulation_metadata.py
libsms/_client/api/simulations/get_ecoli_simulation_outdata.py
libsms/_client/api/simulations/get_ecoli_simulation_status.py
libsms/_client/api/simulations/list_ecoli_simulations.py
libsms-0.2.9.dist-info/WHEEL
libsms-0.2.9.dist-info/METADATA
libsms-0.2.9.dist-info/RECORD
