Metadata-Version: 2.3
Name: libsms
Version: 0.2.9
Summary: Interacting with the Simulating Microbial Systems (SMS Atlantis) API
Requires-Dist: fastapi>=0.118.0
Requires-Dist: httpx>=0.28.1
Requires-Dist: orjson>=3.11.3
Requires-Dist: polars[all]>=1.33.1
Requires-Dist: pydantic>=2.11.9
Requires-Dist: requests>=2.32.5
Requires-Dist: tqdm>=4.67.1
Requires-Dist: uv-build>=0.8.15
Requires-Python: >=3.11
